fedml_aws/__init__.py
fedml_aws/build_and_push.sh
fedml_aws/dbconnection.py
fedml_aws/dwcsagemaker.py
fedml_aws/install_kubectl.sh
fedml_aws/logger.py
fedml_aws/predictor.py
fedml_aws/script_generator.py
fedml_aws-2.0.2.data/scripts/build_and_push.sh
fedml_aws-2.0.2.data/scripts/install_kubectl.sh
fedml_aws-2.0.2.dist-info/METADATA
fedml_aws-2.0.2.dist-info/WHEEL
fedml_aws-2.0.2.dist-info/top_level.txt
fedml_aws-2.0.2.dist-info/RECORD
